[  {    "type": "post",    "url": "/api/send",    "title": "发送短信接口,",    "version": "0.0.1",    "name": "APIsend",    "group": "API",    "description": "<p>所有参数加密成jwt_access_token.</p>",    "parameter": {      "fields": {        "Parameter": [          {            "group": "Parameter",            "type": "String",            "optional": false,            "field": "tel",            "description": "<p>phone NO.</p>"          },          {            "group": "Parameter",            "type": "Number",            "optional": false,            "field": "tpl_id",            "description": "<p>template ID.</p>"          },          {            "group": "Parameter",            "type": "Array",            "optional": false,            "field": "params",            "description": "<p>template content array.</p>"          },          {            "group": "Parameter",            "type": "String",            "optional": false,            "field": "exp",            "description": "<p>13位过期时间.</p>"          }        ]      }    },    "success": {      "fields": {        "Success 200": [          {            "group": "Success 200",            "type": "String",            "optional": false,            "field": "firstname",            "description": "<p>Firstname of the User.</p>"          },          {            "group": "Success 200",            "type": "String",            "optional": false,            "field": "lastname",            "description": "<p>Lastname of the User.</p>"          }        ]      }    },    "filename": "back/routes/api/api.js",    "groupTitle": "API"  }]
